nervous_analytics/__init__.py
nervous_analytics/analyzers/__init__.py
nervous_analytics/analyzers/ecg_analyzer.py
nervous_analytics/analyzers/ecg_analyzer_gui.py
nervous_analytics/analyzers/eda_analyzer.py
nervous_analytics/analyzers/eda_analyzer_gui.py
nervous_analytics/analyzers/eda_decisiontree.py
nervous_analytics-0.3.4.dist-info/LICENSE
nervous_analytics-0.3.4.dist-info/METADATA
nervous_analytics-0.3.4.dist-info/WHEEL
nervous_analytics-0.3.4.dist-info/entry_points.txt
nervous_analytics-0.3.4.dist-info/RECORD
