Metadata-Version: 2.3
Name: nervous-analytics
Version: 0.3.4
Summary: Package implementing modular processes for real-time feature localization on ECG and EDA signals.
License: MIT
Author: Bertrand Massot
Author-email: bertrand.massot@insa-lyon.fr
Requires-Python: >=3.11,<3.14
Classifier: License :: OSI Approved :: MIT License
Classifier: Programming Language :: Python :: 3
Classifier: Programming Language :: Python :: 3.11
Classifier: Programming Language :: Python :: 3.12
Classifier: Programming Language :: Python :: 3.13
Requires-Dist: PyWavelets (>=1.6.0)
Requires-Dist: matplotlib (>=3.8.3)
Requires-Dist: neurokit2 (>=0.2.9)
Requires-Dist: numpy (>=1.26.4)
Requires-Dist: openpyxl (>=3.1.5,<4.0.0)
Requires-Dist: pandas (>=2.2.2)
Requires-Dist: scipy (>=1.14.0)
Requires-Dist: sleepecg (>=0.5.9)
Project-URL: Repository, https://github.com/sensors-inl/Nervous-Sensors
